{
	"activation": {
		"Subject": "Dobrodo\u0161li! Molimo potvrdite svoju adresu e-po\u0161te.",
		"Thanks": "Dobro do\u0161li u {{1}}",
		"ReallyYourEmail": "Je li ovo stvarno va\u0161a adresa e-po\u0161te, {{1}}? Ako je tako, kliknite <a href='{{2}}'>ovdje</a> kako biste postavili lozinku i aktivirali svoj ra\u010dun.",
		"SeeYou": "Vidimo se na <a href='{{1}}'>{{2}}</a> !",
		"OtherwiseClickLink": "U suprotnom kliknite <a href='{{1}}'>ovu poveznicu</a> ."
	},
	"identifier": {
		"Subject": "Dobrodo\u0161li! Potvrdite svoju email adresu."
	},
	"resend": {
		"Subject": "Hej, jesi li zaboravio svoju lozinku?",
		"Thanks": "Hvala na posjeti {{1}}",
		"YouAreReceiving": "Primili ste ovu e-poruku jer je netko unio va\u0161u adresu e-po\u0161te i kliknuo &quot;zaboravljena \u0161ifra&quot;. Ako to niste bili vi, jednostavno ignorirajte ovu poruku.",
		"Reset": "Za ponovno postavljanje zaporke kliknite {{1}}",
		"SetUpPassphrase": "Postavite lozinku",
		"DomainCode": "Ako je web stranica ve\u0107 otvorena u va\u0161em pregledniku, mo\u017eete unijeti kod"
	},
	"SeeYou": "Vidimo se na {{1}}!",
	"LinkToUnsubscribe": "Ovdje je poveznica za <a href='{{1}}'>otkazivanje pretplate</a> ako vi\u0161e ne \u017eelite primati e-poruke."
}